mewtax/__init__.py
mewtax/mewtax.py
mewtax/py.typed
mewtax-0.0.1.dist-info/LICENSE
mewtax-0.0.1.dist-info/METADATA
mewtax-0.0.1.dist-info/WHEEL
mewtax-0.0.1.dist-info/top_level.txt
mewtax-0.0.1.dist-info/RECORD
