Metadata-Version: 2.1
Name: mewtax
Version: 0.0.1
Summary: Differentiable minimization in jax using Newton's method.
Author-email: Martin Schubert <mfschubert@gmail.com>
Maintainer-email: Martin Schubert <mfschubert@gmail.com>
License: MIT License
Keywords: jax,differentiable optimization,metalearning
Requires-Python: >=3.7
License-File: LICENSE
Requires-Dist: jax
Requires-Dist: jaxlib
Provides-Extra: dev
Requires-Dist: bump-my-version ; extra == 'dev'
Requires-Dist: darglint ; extra == 'dev'
Requires-Dist: mypy ; extra == 'dev'
Requires-Dist: pre-commit ; extra == 'dev'
Provides-Extra: tests
Requires-Dist: numpy ; extra == 'tests'
Requires-Dist: parameterized ; extra == 'tests'
Requires-Dist: pytest ; extra == 'tests'
Requires-Dist: pytest-cov ; extra == 'tests'
